taskmonitor/__init__.py
taskmonitor/admin.py
taskmonitor/app_settings.py
taskmonitor/apps.py
taskmonitor/auth_hooks.py
taskmonitor/helpers.py
taskmonitor/managers.py
taskmonitor/models.py
taskmonitor/signals.py
taskmonitor/tasks.py
taskmonitor/urls.py
taskmonitor/views.py
taskmonitor/core/__init__.py
taskmonitor/core/app_names.py
taskmonitor/core/cached_reports.py
taskmonitor/core/celery_queues.py
taskmonitor/core/list_queryset.py
taskmonitor/core/task_logs.py
taskmonitor/core/task_records.py
taskmonitor/core/tasks_cache.py
taskmonitor/management/commands/__init__.py
taskmonitor/management/commands/taskmonitorctl.py
taskmonitor/migrations/0001_initial.py
taskmonitor/migrations/0002_taskreport.py
taskmonitor/migrations/0003_queuedtask.py
taskmonitor/migrations/0004_store_task_params_and_results.py
taskmonitor/migrations/0005_tasklog_current_queue_length_alter_tasklog_priority.py
taskmonitor/migrations/0006_truncate_exceptions.py
taskmonitor/migrations/0007_alter_tasklog_exception.py
taskmonitor/migrations/0008_taskstatistic.py
taskmonitor/migrations/__init__.py
taskmonitor/static/taskmonitor/css/admin.css
taskmonitor/static/taskmonitor/css/reports.css
taskmonitor/static/taskmonitor/css/statistics.css
taskmonitor/static/taskmonitor/css/tasklog.css
taskmonitor/static/taskmonitor/images/Spinner-1s-64px-dark.gif
taskmonitor/static/taskmonitor/images/Spinner-1s-64px-light.gif
taskmonitor/static/taskmonitor/js/highcharts_defaults.js
taskmonitor/static/taskmonitor/vendor/highcharts/highcharts.js
taskmonitor/static/taskmonitor/vendor/highcharts/highcharts.js.map
taskmonitor/templates/admin/taskmonitor/_task_info.html
taskmonitor/templates/admin/taskmonitor/queuedtask/change_list.html
taskmonitor/templates/admin/taskmonitor/report/chart_bar_partial.html
taskmonitor/templates/admin/taskmonitor/report/chart_pie_partial.html
taskmonitor/templates/admin/taskmonitor/report/chart_scatter_partial.html
taskmonitor/templates/admin/taskmonitor/report/chart_throughput_partial.html
aa_taskmonitor-0.23.1.dist-info/LICENSE
aa_taskmonitor-0.23.1.dist-info/WHEEL
aa_taskmonitor-0.23.1.dist-info/METADATA
aa_taskmonitor-0.23.1.dist-info/RECORD
